aldryn_gallery_timed/__init__.py
aldryn_gallery_timed/cms_plugins.py
aldryn_gallery_timed/models.py
aldryn_gallery_timed/migrations/0001_initial.py
aldryn_gallery_timed/migrations/__init__.py
aldryn_gallery_timed/templates/aldryn_gallery/empty.html
aldryn_gallery_timed-0.0.1.dist-info/DESCRIPTION.rst
aldryn_gallery_timed-0.0.1.dist-info/METADATA
aldryn_gallery_timed-0.0.1.dist-info/pydist.json
aldryn_gallery_timed-0.0.1.dist-info/RECORD
aldryn_gallery_timed-0.0.1.dist-info/top_level.txt
aldryn_gallery_timed-0.0.1.dist-info/WHEEL
